xslope/__init__.py
xslope/_version.py
xslope/advanced.py
xslope/fem.py
xslope/fileio.py
xslope/global_config.py
xslope/mesh copy.py
xslope/mesh.py
xslope/plot.py
xslope/plot_fem.py
xslope/plot_seep.py
xslope/search.py
xslope/seep.py
xslope/slice.py
xslope/solve.py
xslope-0.1.14.dist-info/LICENSE
xslope-0.1.14.dist-info/METADATA
xslope-0.1.14.dist-info/NOTICE
xslope-0.1.14.dist-info/WHEEL
xslope-0.1.14.dist-info/top_level.txt
xslope-0.1.14.dist-info/RECORD
