Metadata-Version: 2.2
Name: xslope
Version: 0.1.14
Summary: Slope stability analysis (limit equilibrium and FEM) in Python.
Author: Norman L. Jones
Project-URL: Homepage, https://github.com/njones61/xslope
Project-URL: Documentation, https://xslope.readthedocs.io/en/latest/
Project-URL: Source, https://github.com/njones61/xslope
Project-URL: Issues, https://github.com/njones61/xslope/issues
Keywords: slope,stability,geotechnical,FEM,limit equilibrium
Classifier: License :: OSI Approved :: Apache Software License
Classifier: Programming Language :: Python
Classifier: Programming Language :: Python :: 3
Classifier: Programming Language :: Python :: 3 :: Only
Classifier: Programming Language :: Python :: 3.9
Classifier: Programming Language :: Python :: 3.10
Classifier: Programming Language :: Python :: 3.11
Classifier: Programming Language :: Python :: 3.12
Classifier: Intended Audience :: Science/Research
Classifier: Topic :: Scientific/Engineering
Requires-Python: >=3.9
License-File: LICENSE
License-File: NOTICE
Requires-Dist: numpy
Requires-Dist: pandas
Requires-Dist: matplotlib
Requires-Dist: scipy
Requires-Dist: shapely
Requires-Dist: openpyxl
Provides-Extra: fem
Requires-Dist: gmsh; extra == "fem"
